finitefloat/__init__.py
finitefloat/exceptions.py
finitefloat/finitefloat.py
finitefloat/py.typed
finitefloat-0.1.1.dist-info/LICENSE
finitefloat-0.1.1.dist-info/WHEEL
finitefloat-0.1.1.dist-info/METADATA
finitefloat-0.1.1.dist-info/RECORD
